apple_appstore_metadata_extractor-0.1.12.dist-info/licenses/LICENSE
appstore_metadata_extractor/__init__.py
appstore_metadata_extractor/change_monitor.py
appstore_metadata_extractor/cli.py
appstore_metadata_extractor/models.py
appstore_metadata_extractor/models_combined.py
appstore_metadata_extractor/py.typed
appstore_metadata_extractor/scraper.py
appstore_metadata_extractor/wbs_extractor.py
appstore_metadata_extractor/cli/commands.py
appstore_metadata_extractor/core/__init__.py
appstore_metadata_extractor/core/cache.py
appstore_metadata_extractor/core/exceptions.py
appstore_metadata_extractor/core/extractors.py
appstore_metadata_extractor/core/models.py
appstore_metadata_extractor/core/wbs_validator.py
apple_appstore_metadata_extractor-0.1.12.dist-info/METADATA
apple_appstore_metadata_extractor-0.1.12.dist-info/WHEEL
apple_appstore_metadata_extractor-0.1.12.dist-info/entry_points.txt
apple_appstore_metadata_extractor-0.1.12.dist-info/top_level.txt
apple_appstore_metadata_extractor-0.1.12.dist-info/RECORD
