Metadata-Version: 2.4
Name: apple-appstore-metadata-extractor
Version: 0.1.12
Summary: Extract and monitor metadata from Apple App Store applications
Author-email: Bickster LLC <support@bickster.com>
License: MIT
Project-URL: Homepage, https://github.com/Bickster-LLC/appstore-metadata-extractor-python
Project-URL: Documentation, https://github.com/Bickster-LLC/appstore-metadata-extractor-python#readme
Project-URL: Repository, https://github.com/Bickster-LLC/appstore-metadata-extractor-python
Project-URL: Issues, https://github.com/Bickster-LLC/appstore-metadata-extractor-python/issues
Project-URL: Changelog, https://github.com/Bickster-LLC/appstore-metadata-extractor-python/blob/main/CHANGELOG.md
Keywords: app store,metadata,ios,apple,scraping,monitoring
Classifier: Development Status :: 4 - Beta
Classifier: Intended Audience :: Developers
Classifier: License :: OSI Approved :: MIT License
Classifier: Programming Language :: Python :: 3
Classifier: Programming Language :: Python :: 3.11
Classifier: Programming Language :: Python :: 3.12
Classifier: Programming Language :: Python :: 3.13
Classifier: Topic :: Software Development :: Libraries
Classifier: Topic :: Internet :: WWW/HTTP :: Dynamic Content
Requires-Python: >=3.11
License-File: LICENSE
Requires-Dist: requests>=2.31.0
Requires-Dist: beautifulsoup4>=4.12.0
Requires-Dist: lxml>=4.9.0
Requires-Dist: pydantic>=2.5.0
Requires-Dist: aiohttp>=3.9.0
Requires-Dist: tenacity>=8.2.0
Requires-Dist: rich>=13.7.0
Requires-Dist: click>=8.1.0
Provides-Extra: dev
Requires-Dist: pytest>=7.4.0; extra == "dev"
Requires-Dist: pytest-cov>=4.1.0; extra == "dev"
Requires-Dist: pytest-asyncio>=0.21.0; extra == "dev"
Requires-Dist: black>=23.7.0; extra == "dev"
Requires-Dist: isort>=5.12.0; extra == "dev"
Requires-Dist: flake8>=6.1.0; extra == "dev"
Requires-Dist: mypy>=1.5.0; extra == "dev"
Requires-Dist: pre-commit>=3.3.0; extra == "dev"
Requires-Dist: types-requests>=2.31.0; extra == "dev"
Requires-Dist: types-beautifulsoup4>=4.12.0; extra == "dev"
Requires-Dist: Pillow>=10.0.0; extra == "dev"
Dynamic: license-file
